cs/cmdutils.py
cs_cmdutils-20250724.dist-info/WHEEL
cs_cmdutils-20250724.dist-info/METADATA
cs_cmdutils-20250724.dist-info/RECORD
