Metadata-Version: 2.4
Name: cs-cmdutils
Version: 20250724
Summary: Convenience functions for working with the cmd stdlib module, the BaseCommand class for constructing command line programmes, and other command line related stuff.
Keywords: python2,python3
Author-email: Cameron Simpson <cs@cskk.id.au>
Classifier: Programming Language :: Python
Classifier: Programming Language :: Python :: 3
Classifier: Development Status :: 4 - Beta
Classifier: Intended Audience :: Developers
Classifier: Operating System :: OS Independent
Classifier: Topic :: Software Development :: Libraries :: Python Modules
Classifier: License :: OSI Approved :: GNU General Public License v3 or later (GPLv3+)
Requires-Dist: cs.context>=20250528
Requires-Dist: cs.deco>=20250531
Requires-Dist: cs.lex>=20250724
Requires-Dist: cs.logutils>=20250323
Requires-Dist: cs.pfx>=20250613
Requires-Dist: cs.py.doc>=20250426
Requires-Dist: cs.resources>=20250325
Requires-Dist: cs.result>=20250306
Requires-Dist: cs.threads>=20250528
Requires-Dist: cs.typingutils>=20250503
Requires-Dist: cs.upd>=20250426
Requires-Dist: typeguard
Project-URL: MonoRepo Commits, https://bitbucket.org/cameron_simpson/css/commits/branch/main
Project-URL: Monorepo Git Mirror, https://github.com/cameron-simpson/css
Project-URL: Monorepo Hg/Mercurial Mirror, https://hg.sr.ht/~cameron-simpson/css
Project-URL: Source, https://github.com/cameron-simpson/css/blob/main/lib/python/cs/cmdutils.py
